pyonegame/images/.DS_Store
pyonegame/images/10 of Clubs.png
pyonegame/images/10 of Diamonds.png
pyonegame/images/10 of Hearts.png
pyonegame/images/10 of Spades.png
pyonegame/images/2 of Clubs.png
pyonegame/images/2 of Diamonds.png
pyonegame/images/2 of Hearts.png
pyonegame/images/2 of Spades.png
pyonegame/images/3 of Clubs.png
pyonegame/images/3 of Diamonds.png
pyonegame/images/3 of Hearts.png
pyonegame/images/3 of Spades.png
pyonegame/images/4 of Clubs.png
pyonegame/images/4 of Diamonds.png
pyonegame/images/4 of Hearts.png
pyonegame/images/4 of Spades.png
pyonegame/images/5 of Clubs.png
pyonegame/images/5 of Diamonds.png
pyonegame/images/5 of Hearts.png
pyonegame/images/5 of Spades.png
pyonegame/images/6 of Clubs.png
pyonegame/images/6 of Diamonds.png
pyonegame/images/6 of Hearts.png
pyonegame/images/6 of Spades.png
pyonegame/images/7 of Clubs.png
pyonegame/images/7 of Diamonds.png
pyonegame/images/7 of Hearts.png
pyonegame/images/7 of Spades.png
pyonegame/images/8 of Clubs.png
pyonegame/images/8 of Diamonds.png
pyonegame/images/8 of Hearts.png
pyonegame/images/8 of Spades.png
pyonegame/images/9 of Clubs.png
pyonegame/images/9 of Diamonds.png
pyonegame/images/9 of Hearts.png
pyonegame/images/9 of Spades.png
pyonegame/images/Ace of Clubs.png
pyonegame/images/Ace of Diamonds.png
pyonegame/images/Ace of Hearts.png
pyonegame/images/Ace of Spades.png
pyonegame/images/addDisabled.png
pyonegame/images/addDown.png
pyonegame/images/addNormal.png
pyonegame/images/addOver.png
pyonegame/images/backDisabled.png
pyonegame/images/backDown.png
pyonegame/images/background.png
pyonegame/images/backNormal.png
pyonegame/images/BackOfCard.png
pyonegame/images/backOver.png
pyonegame/images/baddie.png
pyonegame/images/cancelDisabled.png
pyonegame/images/cancelDown.png
pyonegame/images/cancelNormal.png
pyonegame/images/cancelOver.png
pyonegame/images/controlsBackground.jpg
pyonegame/images/dialog.png
pyonegame/images/dodger.png
pyonegame/images/Game.py
pyonegame/images/gameOver.png
pyonegame-1.0.3.dist-info/METADATA
pyonegame-1.0.3.dist-info/WHEEL
pyonegame-1.0.3.dist-info/RECORD
