Metadata-Version: 2.3
Name: pyonegame
Version: 1.0.3
Summary: This library run the game rock, paper, scissors
License: MIT
Keywords: meow
Author: JUMP10
Author-email: loskattilavr5556@gmail.com
Requires-Python: >=3.13
Classifier: License :: OSI Approved :: MIT License
Classifier: Programming Language :: Python :: 3
Classifier: Programming Language :: Python :: 3.13
